geekbench6_client/__init__.py
geekbench6_client/api.py
geekbench6_client/parser.py
geekbench6_client/utils.py
geekbench6_client/parser_handlers/__init__.py
geekbench6_client/parser_handlers/ai_parse_handler.py
geekbench6_client/parser_handlers/cpu_parse_handler.py
geekbench6_client/parser_handlers/gpu_parse_handler.py
geekbench6_client/parser_handlers/latest_cpu_parse_handler.py
geekbench6_client/parser_handlers/login_parse_handler.py
geekbench6_api-1.0.dist-info/LICENSE
geekbench6_api-1.0.dist-info/METADATA
geekbench6_api-1.0.dist-info/WHEEL
geekbench6_api-1.0.dist-info/top_level.txt
geekbench6_api-1.0.dist-info/RECORD
